setup.py
docs/HISTORY.txt
src/megrok/__init__.py
src/megrok.z3cform.composed.egg-info/PKG-INFO
src/megrok.z3cform.composed.egg-info/SOURCES.txt
src/megrok.z3cform.composed.egg-info/dependency_links.txt
src/megrok.z3cform.composed.egg-info/namespace_packages.txt
src/megrok.z3cform.composed.egg-info/not-zip-safe
src/megrok.z3cform.composed.egg-info/requires.txt
src/megrok.z3cform.composed.egg-info/top_level.txt
src/megrok/z3cform/__init__.py
src/megrok/z3cform/composed/README.txt
src/megrok/z3cform/composed/__init__.py
src/megrok/z3cform/composed/composedform.py
src/megrok/z3cform/composed/configure.zcml
src/megrok/z3cform/composed/ftesting.zcml
src/megrok/z3cform/composed/meta.py
src/megrok/z3cform/composed/meta.zcml
src/megrok/z3cform/composed/subform.py
src/megrok/z3cform/composed/tests.py
src/megrok/z3cform/composed/templates/composedform.pt
src/megrok/z3cform/composed/templates/composedtemplate.pt